oceanstream/README.md
oceanstream/TODO.md
oceanstream/__init__.py
oceanstream/adcp/__init__.py
oceanstream/adcp/processor.py
oceanstream/app.py
oceanstream/cli.py
oceanstream/config/__init__.py
oceanstream/config/settings.py
oceanstream/configuration.py
oceanstream/echodata/__init__.py
oceanstream/echodata/calibrate/__init__.py
oceanstream/echodata/calibrate/calibration.py
oceanstream/echodata/calibrate/saildrone.py
oceanstream/echodata/compute/__init__.py
oceanstream/echodata/compute/mvbs.py
oceanstream/echodata/compute/nasc.py
oceanstream/echodata/compute/sv.py
oceanstream/echodata/concat.py
oceanstream/echodata/config.py
oceanstream/echodata/consolidate/__init__.py
oceanstream/echodata/consolidate/depth.py
oceanstream/echodata/convert.py
oceanstream/echodata/denoise/__init__.py
oceanstream/echodata/denoise/attenuation.py
oceanstream/echodata/denoise/background_noise.py
oceanstream/echodata/denoise/denoise.py
oceanstream/echodata/denoise/impulse_noise.py
oceanstream/echodata/denoise/transient_noise.py
oceanstream/echodata/environment/__init__.py
oceanstream/echodata/environment/absorption.py
oceanstream/echodata/environment/blended.py
oceanstream/echodata/environment/copernicus.py
oceanstream/echodata/environment/enrich.py
oceanstream/echodata/environment/geoparquet.py
oceanstream/echodata/environment/sound_speed.py
oceanstream/echodata/plot/__init__.py
oceanstream/echodata/plot/echogram.py
oceanstream/echodata/processor.py
oceanstream/echodata/seabed/__init__.py
oceanstream/echodata/seabed/detection.py
oceanstream/echodata/stac/__init__.py
oceanstream/echodata/stac/echodata_emit.py
oceanstream/echodata/stac/segments.py
oceanstream/echodata/storage.py
oceanstream/geotrack/README.md
oceanstream/geotrack/__init__.py
oceanstream/geotrack/binning.py
oceanstream/geotrack/campaign.py
oceanstream/geotrack/csv_reader.py
oceanstream/geotrack/deduplication.py
oceanstream/geotrack/geoparquet_writer.py
oceanstream/geotrack/interpolation.py
oceanstream/geotrack/metadata.py
oceanstream-0.1.1.dist-info/METADATA
oceanstream-0.1.1.dist-info/WHEEL
oceanstream-0.1.1.dist-info/entry_points.txt
oceanstream-0.1.1.dist-info/licenses/LICENSE
oceanstream-0.1.1.dist-info/RECORD
