Metadata-Version: 2.4
Name: oceanstream
Version: 0.1.1
Summary: Process oceanographic measurements from USVs and write partitioned GeoParquet datasets with geospatial metadata.
License: MIT
License-File: LICENSE
Keywords: oceanography,geoparquet,stac,saildrone,geospatial,usv,marine-data
Author: Andrei Neacsu
Author-email: andrei@oceanstream.io
Requires-Python: >=3.11,<3.13
Classifier: Development Status :: 4 - Beta
Classifier: Environment :: Console
Classifier: Intended Audience :: Science/Research
Classifier: License :: OSI Approved :: MIT License
Classifier: Operating System :: OS Independent
Classifier: Programming Language :: Python :: 3
Classifier: Programming Language :: Python :: 3.11
Classifier: Programming Language :: Python :: 3.12
Classifier: Topic :: Scientific/Engineering :: GIS
Classifier: Topic :: Scientific/Engineering :: Oceanography
Provides-Extra: adcp
Provides-Extra: all
Provides-Extra: echodata
Provides-Extra: echodata-viz
Provides-Extra: geo
Provides-Extra: geotrack
Provides-Extra: multibeam
Requires-Dist: adlfs (>=2024.4.0) ; extra == "echodata" or extra == "all"
Requires-Dist: azure-storage-blob (>=12.19)
Requires-Dist: bottleneck (==1.5.0) ; extra == "echodata" or extra == "all"
Requires-Dist: copernicusmarine (>=1.0.0) ; extra == "echodata" or extra == "all"
Requires-Dist: dask[complete] (==2024.9.0) ; extra == "echodata" or extra == "all"
Requires-Dist: datashader (>=0.16) ; extra == "echodata-viz" or extra == "all"
Requires-Dist: distributed (==2024.9.0) ; extra == "echodata" or extra == "all"
Requires-Dist: fsspec (==2025.3.2) ; extra == "echodata" or extra == "all"
Requires-Dist: geopandas (>=0.14) ; extra == "geotrack" or extra == "all" or extra == "geo"
Requires-Dist: gsw (>=3.6.0) ; extra == "echodata" or extra == "all"
Requires-Dist: hvplot (>=0.9) ; extra == "echodata-viz" or extra == "all"
Requires-Dist: matplotlib (>=3.7) ; extra == "echodata-viz" or extra == "all"
Requires-Dist: netcdf4 (>=1.6) ; extra == "echodata" or extra == "all"
Requires-Dist: numcodecs (==0.14.1) ; extra == "echodata" or extra == "all"
Requires-Dist: numpy (==1.26.4) ; extra == "echodata" or extra == "all"
Requires-Dist: openpyxl (>=3.0) ; extra == "echodata" or extra == "all"
Requires-Dist: pandas (>=2.1)
Requires-Dist: pyarrow (>=14)
Requires-Dist: pynmea2 (>=1.18) ; extra == "geotrack" or extra == "all" or extra == "geo"
Requires-Dist: rich (>=13.7)
Requires-Dist: seabirdscientific (>=2.7) ; extra == "geotrack" or extra == "all" or extra == "geo"
Requires-Dist: shapely (>=2.0) ; extra == "geotrack" or extra == "all" or extra == "geo"
Requires-Dist: tqdm (>=4.66)
Requires-Dist: typer (>=0.12)
Requires-Dist: xarray (==2024.11.0) ; extra == "echodata" or extra == "all"
Requires-Dist: zarr (>=2.16) ; extra == "echodata" or extra == "all"
Project-URL: Homepage, https://oceanstream.io
